inet_nm/__init__.py
inet_nm/_helpers.py
inet_nm/check.py
inet_nm/cli_check.py
inet_nm/cli_commission.py
inet_nm/cli_decommission.py
inet_nm/cli_exec.py
inet_nm/cli_export.py
inet_nm/cli_free.py
inet_nm/cli_inventory.py
inet_nm/cli_tmux.py
inet_nm/cli_tty_from_uid.py
inet_nm/cli_update_commissioned.py
inet_nm/cli_update_from_os.py
inet_nm/commissioner.py
inet_nm/config.py
inet_nm/data_types.py
inet_nm/filelock.py
inet_nm/locking.py
inet_nm/runner_apps.py
inet_nm/runner_base.py
inet_nm/runner_helper.py
inet_nm-0.0.8.dist-info/LICENSE.txt
inet_nm-0.0.8.dist-info/METADATA
inet_nm-0.0.8.dist-info/WHEEL
inet_nm-0.0.8.dist-info/entry_points.txt
inet_nm-0.0.8.dist-info/top_level.txt
inet_nm-0.0.8.dist-info/RECORD
