Metadata-Version: 2.1
Name: inet-nm
Version: 0.0.8
Summary: cli application for managing nodes
Home-page: https://github.com/inetrg/inet-nm
Author: Kevin Weiss
Author-email: weiss.kevin604@gmail.com
License: MIT
Project-URL: Documentation, https://inet-nm.readthedocs.io/en/stable/
Project-URL: Source, https://github.com/inetrg/inet-nm
Project-URL: Changelog, https://github.com/inetrg/inet-nm/blob/master/CHANGELOG.md
Project-URL: Tracker, https://github.com/inetrg/inet-nm/issues
Project-URL: Download, https://pypi.org/project/inet-nm/#files
Platform: any
Classifier: Development Status :: 4 - Beta
Classifier: Programming Language :: Python
Requires-Python: >=3.7
License-File: LICENSE.txt
Requires-Dist: pyudev
Requires-Dist: importlib-metadata ; python_version < "3.8"
Provides-Extra: all
Requires-Dist: inquirer ; extra == 'all'
Requires-Dist: pyusb ; extra == 'all'
Requires-Dist: kw-cp210x-program ; extra == 'all'
Provides-Extra: testing
Requires-Dist: setuptools ; extra == 'testing'
Requires-Dist: pexpect ; extra == 'testing'
Requires-Dist: pytest ; extra == 'testing'
Requires-Dist: pytest-cov ; extra == 'testing'
Requires-Dist: flaky ; extra == 'testing'
